emoji_quiz/__init__.py
emoji_quiz/main.py
emoji_quiz-0.1.dist-info/METADATA
emoji_quiz-0.1.dist-info/WHEEL
emoji_quiz-0.1.dist-info/entry_points.txt
emoji_quiz-0.1.dist-info/top_level.txt
emoji_quiz-0.1.dist-info/RECORD
