Metadata-Version: 2.4
Name: emoji-quiz
Version: 0.1
Summary: Fun CLI game to guess movies using emojis
Home-page: https://github.com/Ayansyd/emoji-quiz
Author: Ayaan Syed
Author-email: syedayyan2002@gmail.com
License: MIT
Classifier: Programming Language :: Python :: 3
Classifier: License :: OSI Approved :: MIT License
Classifier: Operating System :: OS Independent
Requires-Python: >=3.6
Dynamic: author
Dynamic: author-email
Dynamic: classifier
Dynamic: description
Dynamic: description-content-type
Dynamic: home-page
Dynamic: license
Dynamic: requires-python
Dynamic: summary
